config/apis/v1.yaml
config/apis/v2.yaml
config/apis/v3.yaml
config/apis/v4.yaml
config/databases/complex.yaml
config/databases/db1.yaml
config/databases/simple.yaml
config/objects/core.yaml
toy_api/__init__.py
toy_api/app.py
toy_api/cli.py
toy_api/config_discovery.py
toy_api/constants.py
toy_api/dummy_data_generator.py
toy_api/port_utils.py
toy_api/process_manager.py
toy_api/response_generator.py
toy_api/table_generator.py
toy_api-0.0.4.dist-info/licenses/LICENSE.md
toy_api-0.0.4.dist-info/METADATA
toy_api-0.0.4.dist-info/WHEEL
toy_api-0.0.4.dist-info/entry_points.txt
toy_api-0.0.4.dist-info/top_level.txt
toy_api-0.0.4.dist-info/RECORD
