Metadata-Version: 2.4
Name: toy_api
Version: 0.0.4
Summary: Easily configurable test API servers and dummy Database generation for development and testing
Author-email: Brookie Guzder-Williams <bguzder-williams@berkeley.edu>
License: BSd 3-clause
Classifier: Development Status :: 4 - Beta
Classifier: Intended Audience :: Developers
Classifier: Programming Language :: Python :: 3
Classifier: Programming Language :: Python :: 3.8
Classifier: Programming Language :: Python :: 3.9
Classifier: Programming Language :: Python :: 3.10
Classifier: Programming Language :: Python :: 3.11
Classifier: Programming Language :: Python :: 3.12
Classifier: Topic :: Software Development :: Libraries
Classifier: Topic :: Scientific/Engineering
Requires-Python: >=3.11
License-File: LICENSE.md
Requires-Dist: flask
Requires-Dist: click
Requires-Dist: pyyaml
Dynamic: license-file
